{"home":[{"id":"Ft73JFX4VO4E7Pg7EH0Y","views":0,"videoUrl":"","isSeries":true,"title":"JJK","createdAt":{"type":"firestore/timestamp/1.0","seconds":1774519704,"nanoseconds":827000000},"genre":"Action","tags":"","country":"Japan","isTrendingSection":true,"cast":[],"poster":"https://th.bing.com/th/id/OIP.r746APnwNc6gw3QG4_z5VwHaEK?w=295&h=180&c=7&r=0&o=7&pid=1.7&rm=3","updatedAt":{"type":"firestore/timestamp/1.0","seconds":1774519704,"nanoseconds":827000000},"lang":"Hindi","year":"2020","imdbRating":"9.8","titleLower":"jjk","isNewRelease":true,"sendNotification":false,"servers":[],"downloadUrl":"","category":"Anime","trailerUrl":"","description":"fgwgrgwrgg","isFeatured":false,"industry":"Anime","desc":"fgwgrgwrgg"},{"id":"BNpFZvbMo9Lf4abIa62M","isFeatured":true,"description":"Tanjiro Kamado's journey.","genre":"Action","country":"Japan","poster":"https://upload.wikimedia.org/wikipedia/en/2/21/Kimetsu_no_Yaiba_Mugen_Ressha_Hen_Poster.jpg","industry":"Anime","isTrendingSection":true,"isSeries":true,"title":"Demon Slayer","category":"Anime","views":3500,"imdbRating":"8.7","lang":"Japanese","year":"2019","createdAt":{"type":"firestore/timestamp/1.0","seconds":1774519435,"nanoseconds":873000000},"trailerUrl":"https://www.youtube.com/watch?v=21X5lGlDOfg"},{"id":"QkuImaPgMNsVDQreC4j2","isTrendingSection":true,"industry":"Bollywood","poster":"https://upload.wikimedia.org/wikipedia/en/3/39/Jawan_film_poster.jpg","isFeatured":true,"country":"India","genre":"Action","description":"A high-octane action thriller.","trailerUrl":"https://www.youtube.com/watch?v=COv52Qyctws","createdAt":{"type":"firestore/timestamp/1.0","seconds":1774519435,"nanoseconds":455000000},"imdbRating":"7.5","views":4500,"year":"2023","lang":"Hindi","title":"Jawan","category":"Movie","videoUrl":"https://www.youtube.com/watch?v=COv52Qyctws","isSeries":false},{"id":"GLc2Tt1O6PSXtOI0Q6cM","trailerUrl":"https://www.youtube.com/watch?v=21X5lGlDOfg","titleLower":"demon slayer","isNewRelease":true,"servers":[],"sendNotification":false,"downloadUrl":"","category":"Anime","lang":"Japanese","year":"2019","imdbRating":"8.7","desc":"Tanjiro Kamado's journey.","industry":"Anime","description":"Tanjiro Kamado's journey.","isFeatured":true,"createdAt":{"type":"firestore/timestamp/1.0","seconds":1774513513,"nanoseconds":995000000},"isSeries":true,"videoUrl":"","title":"Demon Slayer","views":3500,"updatedAt":{"type":"firestore/timestamp/1.0","seconds":1774515275,"nanoseconds":428000000},"poster":"https://upload.wikimedia.org/wikipedia/en/2/21/Kimetsu_no_Yaiba_Mugen_Ressha_Hen_Poster.jpg","isTrendingSection":true,"cast":[],"tags":"","genre":"Action","country":"Japan"},{"id":"aDJ4lpQHCcboiWNhCq3i","description":"A high-octane action thriller.","isFeatured":true,"industry":"Bollywood","desc":"A high-octane action thriller.","year":"2023","lang":"Hindi","imdbRating":"7.5","sendNotification":false,"servers":[{"name":"Server 1","url":"https://www.youtube.com/watch?v=COv52Qyctws"}],"isNewRelease":true,"titleLower":"jawan","category":"Movie","downloadUrl":"","trailerUrl":"https://www.youtube.com/watch?v=COv52Qyctws","country":"India","tags":"","genre":"Action","isTrendingSection":true,"cast":[],"updatedAt":{"type":"firestore/timestamp/1.0","seconds":1774515220,"nanoseconds":609000000},"poster":"https://upload.wikimedia.org/wikipedia/en/3/39/Jawan_film_poster.jpg","views":4500,"title":"Jawan","isSeries":false,"videoUrl":"https://www.youtube.com/watch?v=COv52Qyctws","createdAt":{"type":"firestore/timestamp/1.0","seconds":1774513513,"nanoseconds":619000000}},{"id":"f25IhnmdtgW6imhqQDJC","createdAt":{"type":"firestore/timestamp/1.0","seconds":1774513511,"nanoseconds":243000000},"views":3500,"isSeries":true,"videoUrl":"","title":"Demon Slayer","cast":[],"isTrendingSection":true,"poster":"https://upload.wikimedia.org/wikipedia/en/2/21/Kimetsu_no_Yaiba_Mugen_Ressha_Hen_Poster.jpg","updatedAt":{"type":"firestore/timestamp/1.0","seconds":1774514300,"nanoseconds":903000000},"tags":"","genre":"Action","country":"Japan","trailerUrl":"https://www.youtube.com/watch?v=21X5lGlDOfg","imdbRating":"8.7","lang":"Japanese","year":"2019","downloadUrl":"","category":"Anime","isNewRelease":true,"titleLower":"demon slayer","sendNotification":false,"servers":[],"industry":"Anime","desc":"Tanjiro Kamado's journey.","isFeatured":true,"description":"Tanjiro Kamado's journey."},{"id":"AV7uqq7xHkqp03YE6ZeE","desc":"A high-octane action thriller.","industry":"Bollywood","isFeatured":true,"description":"A high-octane action thriller.","trailerUrl":"https://www.youtube.com/watch?v=COv52Qyctws","downloadUrl":"","category":"Movie","sendNotification":false,"servers":[{"name":"Server 1","url":"https://www.youtube.com/watch?v=COv52Qyctws"}],"isNewRelease":true,"titleLower":"jawan","imdbRating":"7.5","year":"2023","lang":"Hindi","poster":"https://upload.wikimedia.org/wikipedia/en/3/39/Jawan_film_poster.jpg","updatedAt":{"type":"firestore/timestamp/1.0","seconds":1774513667,"nanoseconds":417000000},"cast":[],"isTrendingSection":false,"country":"India","tags":"","genre":"Action","createdAt":{"type":"firestore/timestamp/1.0","seconds":1774513510,"nanoseconds":872000000},"title":"Jawan","videoUrl":"https://www.youtube.com/watch?v=COv52Qyctws","isSeries":false,"views":4500},{"id":"WfsgMI9cSx27pePGg5Z6","videoUrl":"","isSeries":true,"title":"Demon Slayer","views":3500,"createdAt":{"type":"firestore/timestamp/1.0","seconds":1774513497,"nanoseconds":33000000},"genre":"Action","tags":"","country":"Japan","updatedAt":{"type":"firestore/timestamp/1.0","seconds":1774519276,"nanoseconds":956000000},"poster":"https://upload.wikimedia.org/wikipedia/en/2/21/Kimetsu_no_Yaiba_Mugen_Ressha_Hen_Poster.jpg","isTrendingSection":false,"cast":[],"downloadUrl":"","category":"Anime","isNewRelease":false,"titleLower":"demon slayer","servers":[],"sendNotification":false,"imdbRating":"8.7","lang":"Japanese","year":"2019","trailerUrl":"https://www.youtube.com/watch?v=21X5lGlDOfg","isFeatured":true,"description":"Tanjiro Kamado's journey.","desc":"Tanjiro Kamado's journey.","industry":"Anime"},{"id":"GmINfZlpbZJAZS35xLab","views":4500,"videoUrl":"https://www.youtube.com/watch?v=COv52Qyctws","isSeries":false,"title":"Jawan","createdAt":{"type":"firestore/timestamp/1.0","seconds":1774513496,"nanoseconds":657000000},"genre":"Action","tags":"","country":"India","isTrendingSection":true,"cast":[],"poster":"https://upload.wikimedia.org/wikipedia/en/3/39/Jawan_film_poster.jpg","updatedAt":{"type":"firestore/timestamp/1.0","seconds":1774519452,"nanoseconds":145000000},"imdbRating":"7.5","lang":"Hindi","year":"2023","downloadUrl":"","category":"Movie","isNewRelease":false,"titleLower":"jawan","sendNotification":false,"servers":[{"url":"https://www.youtube.com/watch?v=COv52Qyctws","name":"Server 1"}],"trailerUrl":"https://www.youtube.com/watch?v=COv52Qyctws","isFeatured":true,"description":"A high-octane action thriller.","industry":"Bollywood","desc":"A high-octane action thriller."}],"trending":[{"id":"QkuImaPgMNsVDQreC4j2","isTrendingSection":true,"industry":"Bollywood","poster":"https://upload.wikimedia.org/wikipedia/en/3/39/Jawan_film_poster.jpg","isFeatured":true,"country":"India","genre":"Action","description":"A high-octane action thriller.","trailerUrl":"https://www.youtube.com/watch?v=COv52Qyctws","createdAt":{"type":"firestore/timestamp/1.0","seconds":1774519435,"nanoseconds":455000000},"imdbRating":"7.5","views":4500,"year":"2023","lang":"Hindi","title":"Jawan","category":"Movie","videoUrl":"https://www.youtube.com/watch?v=COv52Qyctws","isSeries":false},{"id":"aDJ4lpQHCcboiWNhCq3i","description":"A high-octane action thriller.","isFeatured":true,"industry":"Bollywood","desc":"A high-octane action thriller.","year":"2023","lang":"Hindi","imdbRating":"7.5","sendNotification":false,"servers":[{"name":"Server 1","url":"https://www.youtube.com/watch?v=COv52Qyctws"}],"isNewRelease":true,"titleLower":"jawan","category":"Movie","downloadUrl":"","trailerUrl":"https://www.youtube.com/watch?v=COv52Qyctws","country":"India","tags":"","genre":"Action","isTrendingSection":true,"cast":[],"updatedAt":{"type":"firestore/timestamp/1.0","seconds":1774515220,"nanoseconds":609000000},"poster":"https://upload.wikimedia.org/wikipedia/en/3/39/Jawan_film_poster.jpg","views":4500,"title":"Jawan","isSeries":false,"videoUrl":"https://www.youtube.com/watch?v=COv52Qyctws","createdAt":{"type":"firestore/timestamp/1.0","seconds":1774513513,"nanoseconds":619000000}},{"id":"GmINfZlpbZJAZS35xLab","views":4500,"videoUrl":"https://www.youtube.com/watch?v=COv52Qyctws","isSeries":false,"title":"Jawan","createdAt":{"type":"firestore/timestamp/1.0","seconds":1774513496,"nanoseconds":657000000},"genre":"Action","tags":"","country":"India","isTrendingSection":true,"cast":[],"poster":"https://upload.wikimedia.org/wikipedia/en/3/39/Jawan_film_poster.jpg","updatedAt":{"type":"firestore/timestamp/1.0","seconds":1774519452,"nanoseconds":145000000},"imdbRating":"7.5","lang":"Hindi","year":"2023","downloadUrl":"","category":"Movie","isNewRelease":false,"titleLower":"jawan","sendNotification":false,"servers":[{"url":"https://www.youtube.com/watch?v=COv52Qyctws","name":"Server 1"}],"trailerUrl":"https://www.youtube.com/watch?v=COv52Qyctws","isFeatured":true,"description":"A high-octane action thriller.","industry":"Bollywood","desc":"A high-octane action thriller."},{"id":"BNpFZvbMo9Lf4abIa62M","isFeatured":true,"description":"Tanjiro Kamado's journey.","genre":"Action","country":"Japan","poster":"https://upload.wikimedia.org/wikipedia/en/2/21/Kimetsu_no_Yaiba_Mugen_Ressha_Hen_Poster.jpg","industry":"Anime","isTrendingSection":true,"isSeries":true,"title":"Demon Slayer","category":"Anime","views":3500,"imdbRating":"8.7","lang":"Japanese","year":"2019","createdAt":{"type":"firestore/timestamp/1.0","seconds":1774519435,"nanoseconds":873000000},"trailerUrl":"https://www.youtube.com/watch?v=21X5lGlDOfg"},{"id":"GLc2Tt1O6PSXtOI0Q6cM","trailerUrl":"https://www.youtube.com/watch?v=21X5lGlDOfg","titleLower":"demon slayer","isNewRelease":true,"servers":[],"sendNotification":false,"downloadUrl":"","category":"Anime","lang":"Japanese","year":"2019","imdbRating":"8.7","desc":"Tanjiro Kamado's journey.","industry":"Anime","description":"Tanjiro Kamado's journey.","isFeatured":true,"createdAt":{"type":"firestore/timestamp/1.0","seconds":1774513513,"nanoseconds":995000000},"isSeries":true,"videoUrl":"","title":"Demon Slayer","views":3500,"updatedAt":{"type":"firestore/timestamp/1.0","seconds":1774515275,"nanoseconds":428000000},"poster":"https://upload.wikimedia.org/wikipedia/en/2/21/Kimetsu_no_Yaiba_Mugen_Ressha_Hen_Poster.jpg","isTrendingSection":true,"cast":[],"tags":"","genre":"Action","country":"Japan"},{"id":"f25IhnmdtgW6imhqQDJC","createdAt":{"type":"firestore/timestamp/1.0","seconds":1774513511,"nanoseconds":243000000},"views":3500,"isSeries":true,"videoUrl":"","title":"Demon Slayer","cast":[],"isTrendingSection":true,"poster":"https://upload.wikimedia.org/wikipedia/en/2/21/Kimetsu_no_Yaiba_Mugen_Ressha_Hen_Poster.jpg","updatedAt":{"type":"firestore/timestamp/1.0","seconds":1774514300,"nanoseconds":903000000},"tags":"","genre":"Action","country":"Japan","trailerUrl":"https://www.youtube.com/watch?v=21X5lGlDOfg","imdbRating":"8.7","lang":"Japanese","year":"2019","downloadUrl":"","category":"Anime","isNewRelease":true,"titleLower":"demon slayer","sendNotification":false,"servers":[],"industry":"Anime","desc":"Tanjiro Kamado's journey.","isFeatured":true,"description":"Tanjiro Kamado's journey."},{"id":"Ft73JFX4VO4E7Pg7EH0Y","views":0,"videoUrl":"","isSeries":true,"title":"JJK","createdAt":{"type":"firestore/timestamp/1.0","seconds":1774519704,"nanoseconds":827000000},"genre":"Action","tags":"","country":"Japan","isTrendingSection":true,"cast":[],"poster":"https://th.bing.com/th/id/OIP.r746APnwNc6gw3QG4_z5VwHaEK?w=295&h=180&c=7&r=0&o=7&pid=1.7&rm=3","updatedAt":{"type":"firestore/timestamp/1.0","seconds":1774519704,"nanoseconds":827000000},"lang":"Hindi","year":"2020","imdbRating":"9.8","titleLower":"jjk","isNewRelease":true,"sendNotification":false,"servers":[],"downloadUrl":"","category":"Anime","trailerUrl":"","description":"fgwgrgwrgg","isFeatured":false,"industry":"Anime","desc":"fgwgrgwrgg"}],"newRelease":[{"id":"Ft73JFX4VO4E7Pg7EH0Y","views":0,"videoUrl":"","isSeries":true,"title":"JJK","createdAt":{"type":"firestore/timestamp/1.0","seconds":1774519704,"nanoseconds":827000000},"genre":"Action","tags":"","country":"Japan","isTrendingSection":true,"cast":[],"poster":"https://th.bing.com/th/id/OIP.r746APnwNc6gw3QG4_z5VwHaEK?w=295&h=180&c=7&r=0&o=7&pid=1.7&rm=3","updatedAt":{"type":"firestore/timestamp/1.0","seconds":1774519704,"nanoseconds":827000000},"lang":"Hindi","year":"2020","imdbRating":"9.8","titleLower":"jjk","isNewRelease":true,"sendNotification":false,"servers":[],"downloadUrl":"","category":"Anime","trailerUrl":"","description":"fgwgrgwrgg","isFeatured":false,"industry":"Anime","desc":"fgwgrgwrgg"},{"id":"GLc2Tt1O6PSXtOI0Q6cM","trailerUrl":"https://www.youtube.com/watch?v=21X5lGlDOfg","titleLower":"demon slayer","isNewRelease":true,"servers":[],"sendNotification":false,"downloadUrl":"","category":"Anime","lang":"Japanese","year":"2019","imdbRating":"8.7","desc":"Tanjiro Kamado's journey.","industry":"Anime","description":"Tanjiro Kamado's journey.","isFeatured":true,"createdAt":{"type":"firestore/timestamp/1.0","seconds":1774513513,"nanoseconds":995000000},"isSeries":true,"videoUrl":"","title":"Demon Slayer","views":3500,"updatedAt":{"type":"firestore/timestamp/1.0","seconds":1774515275,"nanoseconds":428000000},"poster":"https://upload.wikimedia.org/wikipedia/en/2/21/Kimetsu_no_Yaiba_Mugen_Ressha_Hen_Poster.jpg","isTrendingSection":true,"cast":[],"tags":"","genre":"Action","country":"Japan"},{"id":"aDJ4lpQHCcboiWNhCq3i","description":"A high-octane action thriller.","isFeatured":true,"industry":"Bollywood","desc":"A high-octane action thriller.","year":"2023","lang":"Hindi","imdbRating":"7.5","sendNotification":false,"servers":[{"name":"Server 1","url":"https://www.youtube.com/watch?v=COv52Qyctws"}],"isNewRelease":true,"titleLower":"jawan","category":"Movie","downloadUrl":"","trailerUrl":"https://www.youtube.com/watch?v=COv52Qyctws","country":"India","tags":"","genre":"Action","isTrendingSection":true,"cast":[],"updatedAt":{"type":"firestore/timestamp/1.0","seconds":1774515220,"nanoseconds":609000000},"poster":"https://upload.wikimedia.org/wikipedia/en/3/39/Jawan_film_poster.jpg","views":4500,"title":"Jawan","isSeries":false,"videoUrl":"https://www.youtube.com/watch?v=COv52Qyctws","createdAt":{"type":"firestore/timestamp/1.0","seconds":1774513513,"nanoseconds":619000000}},{"id":"f25IhnmdtgW6imhqQDJC","createdAt":{"type":"firestore/timestamp/1.0","seconds":1774513511,"nanoseconds":243000000},"views":3500,"isSeries":true,"videoUrl":"","title":"Demon Slayer","cast":[],"isTrendingSection":true,"poster":"https://upload.wikimedia.org/wikipedia/en/2/21/Kimetsu_no_Yaiba_Mugen_Ressha_Hen_Poster.jpg","updatedAt":{"type":"firestore/timestamp/1.0","seconds":1774514300,"nanoseconds":903000000},"tags":"","genre":"Action","country":"Japan","trailerUrl":"https://www.youtube.com/watch?v=21X5lGlDOfg","imdbRating":"8.7","lang":"Japanese","year":"2019","downloadUrl":"","category":"Anime","isNewRelease":true,"titleLower":"demon slayer","sendNotification":false,"servers":[],"industry":"Anime","desc":"Tanjiro Kamado's journey.","isFeatured":true,"description":"Tanjiro Kamado's journey."},{"id":"AV7uqq7xHkqp03YE6ZeE","desc":"A high-octane action thriller.","industry":"Bollywood","isFeatured":true,"description":"A high-octane action thriller.","trailerUrl":"https://www.youtube.com/watch?v=COv52Qyctws","downloadUrl":"","category":"Movie","sendNotification":false,"servers":[{"name":"Server 1","url":"https://www.youtube.com/watch?v=COv52Qyctws"}],"isNewRelease":true,"titleLower":"jawan","imdbRating":"7.5","year":"2023","lang":"Hindi","poster":"https://upload.wikimedia.org/wikipedia/en/3/39/Jawan_film_poster.jpg","updatedAt":{"type":"firestore/timestamp/1.0","seconds":1774513667,"nanoseconds":417000000},"cast":[],"isTrendingSection":false,"country":"India","tags":"","genre":"Action","createdAt":{"type":"firestore/timestamp/1.0","seconds":1774513510,"nanoseconds":872000000},"title":"Jawan","videoUrl":"https://www.youtube.com/watch?v=COv52Qyctws","isSeries":false,"views":4500}],"lastUpdated":"2026-03-26T10:08:28.191Z"}